README.rst
distribute_setup.py
setup.py
quix/__init__.py
quix.django.contact.egg-info/PKG-INFO
quix.django.contact.egg-info/SOURCES.txt
quix.django.contact.egg-info/dependency_links.txt
quix.django.contact.egg-info/namespace_packages.txt
quix.django.contact.egg-info/top_level.txt
quix/django/__init__.py
quix/django/contact/__init__.py
quix/django/contact/forms.py
quix/django/contact/urls.py
quix/django/contact/views.py